safa/__init__.py
safa/constants.py
safa/runner.py
safa/tool_registrar.py
safa/api/__init__.py
safa/api/client_factory.py
safa/api/constants.py
safa/api/http_client.py
safa/api/safa_client.py
safa/api/safa_store.py
safa/config/README.md
safa/config/__init__.py
safa/config/base_config.py
safa/config/factory.py
safa/config/llm_config.py
safa/config/project_config.py
safa/config/repo_config.py
safa/config/safa_config.py
safa/config/user_config.py
safa/data/__init__.py
safa/data/artifact.py
safa/data/commits.py
safa/data/file_change.py
safa/tools/__init__.py
safa/tools/committer.py
safa/tools/configure.py
safa/tools/jobs.py
safa/tools/search.py
safa/tools/projects/__init__.py
safa/tools/projects/configure.py
safa/tools/projects/create.py
safa/tools/projects/delete.py
safa/tools/projects/push.py
safa/tools/projects/refresh.py
safa/tools/projects/select.py
safa/utils/__init__.py
safa/utils/commit_store.py
safa/utils/commits.py
safa/utils/dates.py
safa/utils/diff_summary.py
safa/utils/diffs.py
safa/utils/fs.py
safa/utils/git_helpers.py
safa/utils/llm_manager.py
safa/utils/markdown.py
safa/utils/menus/__init__.py
safa/utils/menus/inputs.py
safa/utils/menus/menu.py
safa/utils/menus/page_menu.py
safa/utils/menus/printers.py
safa/utils/menus/properties.py
safa-0.1.0.dist-info/METADATA
safa-0.1.0.dist-info/WHEEL
safa-0.1.0.dist-info/entry_points.txt
safa-0.1.0.dist-info/RECORD
