Metadata-Version: 2.3
Name: safa
Version: 0.1.0
Summary: A command line tool for running SAFA in the command line.
Author-email: Alberto Rodriguez <alberto@safa.ai.com>
License: MIT
Requires-Python: >=3.10
Requires-Dist: anthropic==0.30.1
Requires-Dist: certifi==2024.6.2
Requires-Dist: gitpython==3.1.43
Requires-Dist: langchain-anthropic==0.1.19
Requires-Dist: langchain-chroma==0.1.2
Requires-Dist: langchain-community==0.2.6
Requires-Dist: langchain-core==0.2.11
Requires-Dist: langchain-huggingface==0.0.3
Requires-Dist: langchain-text-splitters==0.2.2
Requires-Dist: langchain==0.2.6
Requires-Dist: python-dotenv==1.0.1
Requires-Dist: requests==2.32.3
Requires-Dist: sentence-transformers==3.0.1
